[
    {
        "title": "E14 Batch",
        "url": "/students/e14"
    },
    {
        "title": "E13 Batch",
        "url": "/students/e13"
    },
    {
        "title": "E12 Batch",
        "url": "/students/e12"
    },
    {
        "title": "E11 Batch",
        "url": "/students/e11"
    },
    {
        "title": "E10 Batch",
        "url": "/students/e10"
    },
    {
        "title": "E09 Batch",
        "url": "http://www.ce.pdn.ac.lk/e-09-students"
    },
    {
        "title": "E08 Batch",
        "url": "http://www.ce.pdn.ac.lk/e-08-batch"
    },
    {
        "title": "E06 Batch",
        "url": "http://www.ce.pdn.ac.lk/e-06-batch"
    },
    {
        "title": "E05 Batch",
        "url": "http://www.ce.pdn.ac.lk/e-05-batch"
    },
    {
        "title": "E04 Batch",
        "url": "http://www.ce.pdn.ac.lk/e-04-batch"
    },
    {
        "title": "E03 Batch",
        "url": "http://www.ce.pdn.ac.lk/e-03-students"
    },
    {
        "title": "E02A Batch",
        "url": "http://www.ce.pdn.ac.lk/e-02-a-final-results"
    },
]
